{
  "pedidos": 
  [
	  {
		"idMarca": "1",
		"acuerdo": "207803",
		"fecha": 1552280400000,
		"codigoCliente": "003115",
		"codigoObra": "MT41",
		"obra": "C.C EL POLO",
		"pedido": "256",
		"direccion": "AVE EL POLO 695, FRENTE AL CENTRO COMERCIAL EL POLO . - SANTIAGO DE SURCO / G-301119-EN LA MISMA AV EL POLO",
		"horaInicio": "10:00",
		"estado": "EN ATENCIÓN",
		"despachos": [
		  {
			"codigo": "48",
			"camion": "448",
			"elemento": "Losa",
			"planta": "VILLA 3 UNICON",
			"plantaCodigo": "UV3",
			"guia": "339-0005124",
			"volumen": "7.50",
			"horaSalida": "09:41",
			"horaLlegada": "10:12 (Estimado)",
			"teo": "0.00",
			"horaInicioVaciado": "",
			"horaFinVaciado": "",
			"estado": "2",
			"cantAjuste": "0.00",
			"tipo": "MIXER",
			"volumenTotal": "89.00",
			"tipoPedido": "CONCRETO Y SERVICIO DE BOMBA",
			"disenho": "1280N67B",
			"frecuencia": "25.00",
			"latitud": -12.1013333333,
			"longitud": -76.971695
		  },
		  {
			"codigo": "49",
			"camion": "563",
			"elemento": "Losa",
			"planta": "VILLA 3 UNICON",
			"plantaCodigo": "UV3",
			"guia": "339-0005127",
			"volumen": "7.50",
			"horaSalida": "10:06",
			"horaLlegada": "10:39 (Estimado)",
			"teo": "0.00",
			"horaInicioVaciado": "",
			"horaFinVaciado": "",
			"estado": "2",
			"cantAjuste": "0.00",
			"tipo": "MIXER",
			"volumenTotal": "89.00",
			"tipoPedido": "CONCRETO Y SERVICIO DE BOMBA",
			"disenho": "1280N67B",
			"frecuencia": "25.00",
			"latitud": -12.0983733333,
			"longitud": -76.9719083333
		  },
		  {
			"codigo": "50",
			"camion": "708",
			"elemento": "Losa",
			"planta": "VILLA 3 UNICON",
			"plantaCodigo": "UV3",
			"guia": "339-0005130",
			"volumen": "7.50",
			"horaSalida": "",
			"horaLlegada": "",
			"teo": "0.00",
			"horaInicioVaciado": "",
			"horaFinVaciado": "",
			"estado": "1",
			"cantAjuste": "0.00",
			"tipo": "MIXER",
			"volumenTotal": "89.00",
			"tipoPedido": "CONCRETO Y SERVICIO DE BOMBA",
			"disenho": "1280N67B",
			"frecuencia": "25.00",
			"latitud": 0,
			"longitud": 0
		  },
		  {
			"codigo": "51",
			"camion": "",
			"elemento": "Losa",
			"planta": "",
			"plantaCodigo": "",
			"guia": "",
			"volumen": "7.50",
			"horaSalida": "",
			"horaLlegada": "",
			"teo": "",
			"horaInicioVaciado": "",
			"horaFinVaciado": "",
			"estado": "1",
			"cantAjuste": "0.00",
			"tipo": "MIXER",
			"volumenTotal": "89.00",
			"tipoPedido": "CONCRETO Y SERVICIO DE BOMBA",
			"disenho": "1280N67B",
			"frecuencia": "25.00",
			"latitud": 0,
			"longitud": 0
		  },
		  {
			"codigo": "52",
			"camion": "",
			"elemento": "Losa",
			"planta": "",
			"plantaCodigo": "",
			"guia": "",
			"volumen": "7.50",
			"horaSalida": "",
			"horaLlegada": "",
			"teo": "",
			"horaInicioVaciado": "",
			"horaFinVaciado": "",
			"estado": "1",
			"cantAjuste": "0.00",
			"tipo": "MIXER",
			"volumenTotal": "89.00",
			"tipoPedido": "CONCRETO Y SERVICIO DE BOMBA",
			"disenho": "1280N67B",
			"frecuencia": "25.00",
			"latitud": 0,
			"longitud": 0
		  },
		  {
			"codigo": "53",
			"camion": "",
			"elemento": "Losa",
			"planta": "",
			"plantaCodigo": "",
			"guia": "",
			"volumen": "7.50",
			"horaSalida": "",
			"horaLlegada": "",
			"teo": "",
			"horaInicioVaciado": "",
			"horaFinVaciado": "",
			"estado": "1",
			"cantAjuste": "0.00",
			"tipo": "MIXER",
			"volumenTotal": "89.00",
			"tipoPedido": "CONCRETO Y SERVICIO DE BOMBA",
			"disenho": "1280N67B",
			"frecuencia": "25.00",
			"latitud": 0,
			"longitud": 0
		  },
		  {
			"codigo": "54",
			"camion": "",
			"elemento": "Losa",
			"planta": "",
			"plantaCodigo": "",
			"guia": "",
			"volumen": "7.50",
			"horaSalida": "",
			"horaLlegada": "",
			"teo": "",
			"horaInicioVaciado": "",
			"horaFinVaciado": "",
			"estado": "1",
			"cantAjuste": "0.00",
			"tipo": "MIXER",
			"volumenTotal": "89.00",
			"tipoPedido": "CONCRETO Y SERVICIO DE BOMBA",
			"disenho": "1280N67B",
			"frecuencia": "25.00",
			"latitud": 0,
			"longitud": 0
		  },
		  {
			"codigo": "55",
			"camion": "",
			"elemento": "Losa",
			"planta": "",
			"plantaCodigo": "",
			"guia": "",
			"volumen": "7.50",
			"horaSalida": "",
			"horaLlegada": "",
			"teo": "",
			"horaInicioVaciado": "",
			"horaFinVaciado": "",
			"estado": "1",
			"cantAjuste": "0.00",
			"tipo": "MIXER",
			"volumenTotal": "89.00",
			"tipoPedido": "CONCRETO Y SERVICIO DE BOMBA",
			"disenho": "1280N67B",
			"frecuencia": "25.00",
			"latitud": 0,
			"longitud": 0
		  },
		  {
			"codigo": "56",
			"camion": "",
			"elemento": "Losa",
			"planta": "",
			"plantaCodigo": "",
			"guia": "",
			"volumen": "7.50",
			"horaSalida": "",
			"horaLlegada": "",
			"teo": "",
			"horaInicioVaciado": "",
			"horaFinVaciado": "",
			"estado": "1",
			"cantAjuste": "0.00",
			"tipo": "MIXER",
			"volumenTotal": "89.00",
			"tipoPedido": "CONCRETO Y SERVICIO DE BOMBA",
			"disenho": "1280N67B",
			"frecuencia": "25.00",
			"latitud": 0,
			"longitud": 0
		  },
		  {
			"codigo": "57",
			"camion": "",
			"elemento": "Losa",
			"planta": "",
			"plantaCodigo": "",
			"guia": "",
			"volumen": "7.50",
			"horaSalida": "",
			"horaLlegada": "",
			"teo": "",
			"horaInicioVaciado": "",
			"horaFinVaciado": "",
			"estado": "1",
			"cantAjuste": "0.00",
			"tipo": "MIXER",
			"volumenTotal": "89.00",
			"tipoPedido": "CONCRETO Y SERVICIO DE BOMBA",
			"disenho": "1280N67B",
			"frecuencia": "25.00",
			"latitud": 0,
			"longitud": 0
		  },
		  {
			"codigo": "58",
			"camion": "",
			"elemento": "Losa",
			"planta": "",
			"plantaCodigo": "",
			"guia": "",
			"volumen": "7.50",
			"horaSalida": "",
			"horaLlegada": "",
			"teo": "",
			"horaInicioVaciado": "",
			"horaFinVaciado": "",
			"estado": "1",
			"cantAjuste": "0.00",
			"tipo": "MIXER",
			"volumenTotal": "89.00",
			"tipoPedido": "CONCRETO Y SERVICIO DE BOMBA",
			"disenho": "1280N67B",
			"frecuencia": "25.00",
			"latitud": 0,
			"longitud": 0
		  },
		  {
			"codigo": "59",
			"camion": "",
			"elemento": "Losa",
			"planta": "",
			"plantaCodigo": "",
			"guia": "",
			"volumen": "6.50",
			"horaSalida": "",
			"horaLlegada": "",
			"teo": "",
			"horaInicioVaciado": "",
			"horaFinVaciado": "",
			"estado": "1",
			"cantAjuste": "0.00",
			"tipo": "MIXER",
			"volumenTotal": "89.00",
			"tipoPedido": "CONCRETO Y SERVICIO DE BOMBA",
			"disenho": "1280N67B",
			"frecuencia": "25.00",
			"latitud": 0,
			"longitud": 0
		  },
		  {
			"codigo": "90",
			"camion": "151",
			"elemento": "",
			"planta": "Planta Camion Bombas Pluma",
			"plantaCodigo": "ZCB",
			"guia": "001-9915070",
			"volumen": "89.00",
			"horaSalida": "09:27",
			"horaLlegada": "",
			"teo": "0.00",
			"horaInicioVaciado": "",
			"horaFinVaciado": "",
			"estado": "2",
			"cantAjuste": "0.00",
			"tipo": "BOMBA",
			"volumenTotal": "89.00",
			"tipoPedido": "CONCRETO Y SERVICIO DE BOMBA",
			"disenho": "",
			"frecuencia": "0.00",
			"latitud": 0,
			"longitud": 0
		  }
		],
		"volumenTotal": "",
		"tipoPedido": "",
		"disenho": "",
		"frecuencia": "",
		"volumenAvance": "",
		"totalTiquete": "",
		"numeroTiquete": ""
	  },
	  {
		"idMarca": "1",
		"acuerdo": "208170",
		"fecha": 1552280400000,
		"codigoCliente": "003115",
		"codigoObra": "LA18",
		"obra": "EDIFICIO GRAN COLONIAL",
		"pedido": "22",
		"direccion": "AVE OSCAR R. BENAVIDES (EX COLONIAL) 866 - LIMA / G-251019-",
		"horaInicio": "14:30",
		"estado": "CONFIRMADO",
		"despachos": [
		  {
			"codigo": "1",
			"camion": "",
			"elemento": "Losa",
			"planta": "",
			"plantaCodigo": "",
			"guia": "",
			"volumen": "8.00",
			"horaSalida": "",
			"horaLlegada": "",
			"teo": "",
			"horaInicioVaciado": "",
			"horaFinVaciado": "",
			"estado": "1",
			"cantAjuste": "0.00",
			"tipo": "MIXER",
			"volumenTotal": "23.00",
			"tipoPedido": "CONCRETO",
			"disenho": "1210N57B",
			"frecuencia": "30.00",
			"latitud": 0,
			"longitud": 0
		  },
		  {
			"codigo": "2",
			"camion": "",
			"elemento": "Losa",
			"planta": "",
			"plantaCodigo": "",
			"guia": "",
			"volumen": "8.00",
			"horaSalida": "",
			"horaLlegada": "",
			"teo": "",
			"horaInicioVaciado": "",
			"horaFinVaciado": "",
			"estado": "1",
			"cantAjuste": "0.00",
			"tipo": "MIXER",
			"volumenTotal": "23.00",
			"tipoPedido": "CONCRETO",
			"disenho": "1210N57B",
			"frecuencia": "30.00",
			"latitud": 0,
			"longitud": 0
		  },
		  {
			"codigo": "3",
			"camion": "",
			"elemento": "Losa",
			"planta": "",
			"plantaCodigo": "",
			"guia": "",
			"volumen": "7.00",
			"horaSalida": "",
			"horaLlegada": "",
			"teo": "",
			"horaInicioVaciado": "",
			"horaFinVaciado": "",
			"estado": "1",
			"cantAjuste": "0.00",
			"tipo": "MIXER",
			"volumenTotal": "23.00",
			"tipoPedido": "CONCRETO",
			"disenho": "1210N57B",
			"frecuencia": "30.00",
			"latitud": 0,
			"longitud": 0
		  }
		],
		"volumenTotal": "",
		"tipoPedido": "",
		"disenho": "",
		"frecuencia": "",
		"volumenAvance": "",
		"totalTiquete": "",
		"numeroTiquete": ""
	  },
	  {
		"idMarca": "1",
		"acuerdo": "208170",
		"fecha": 1552280400000,
		"codigoCliente": "003115",
		"codigoObra": "LA18",
		"obra": "EDIFICIO GRAN COLONIAL",
		"pedido": "23",
		"direccion": "AVE OSCAR R. BENAVIDES (EX COLONIAL) 866 - LIMA / G-251019-",
		"horaInicio": "16:00",
		"estado": "CONFIRMADO",
		"despachos": [
		  {
			"codigo": "4",
			"camion": "",
			"elemento": "Columna",
			"planta": "",
			"plantaCodigo": "",
			"guia": "",
			"volumen": "8.00",
			"horaSalida": "",
			"horaLlegada": "",
			"teo": "",
			"horaInicioVaciado": "",
			"horaFinVaciado": "",
			"estado": "1",
			"cantAjuste": "0.00",
			"tipo": "MIXER",
			"volumenTotal": "18.00",
			"tipoPedido": "CONCRETO",
			"disenho": "1210N67B",
			"frecuencia": "40.00",
			"latitud": 0,
			"longitud": 0
		  },
		  {
			"codigo": "5",
			"camion": "",
			"elemento": "Columna",
			"planta": "",
			"plantaCodigo": "",
			"guia": "",
			"volumen": "5.00",
			"horaSalida": "",
			"horaLlegada": "",
			"teo": "",
			"horaInicioVaciado": "",
			"horaFinVaciado": "",
			"estado": "1",
			"cantAjuste": "0.00",
			"tipo": "MIXER",
			"volumenTotal": "18.00",
			"tipoPedido": "CONCRETO",
			"disenho": "1210N67B",
			"frecuencia": "40.00",
			"latitud": 0,
			"longitud": 0
		  },
		  {
			"codigo": "6",
			"camion": "",
			"elemento": "Columna",
			"planta": "",
			"plantaCodigo": "",
			"guia": "",
			"volumen": "5.00",
			"horaSalida": "",
			"horaLlegada": "",
			"teo": "",
			"horaInicioVaciado": "",
			"horaFinVaciado": "",
			"estado": "1",
			"cantAjuste": "0.00",
			"tipo": "MIXER",
			"volumenTotal": "18.00",
			"tipoPedido": "CONCRETO",
			"disenho": "1210N67B",
			"frecuencia": "40.00",
			"latitud": 0,
			"longitud": 0
		  }
		],
		"volumenTotal": "",
		"tipoPedido": "",
		"disenho": "",
		"frecuencia": "",
		"volumenAvance": "",
		"totalTiquete": "",
		"numeroTiquete": ""
	  },
	  {
		"idMarca": "1",
		"acuerdo": "208170",
		"fecha": 1552280400000,
		"codigoCliente": "003115",
		"codigoObra": "LA18",
		"obra": "EDIFICIO GRAN COLONIAL",
		"pedido": "313",
		"direccion": "AVE OSCAR R. BENAVIDES (EX COLONIAL) 866 - LIMA / G-251019-",
		"horaInicio": "17:30",
		"estado": "CONFIRMADO",
		"despachos": [
		  {
			"codigo": "67",
			"camion": "",
			"elemento": "Columna",
			"planta": "",
			"plantaCodigo": "",
			"guia": "",
			"volumen": "8.00",
			"horaSalida": "",
			"horaLlegada": "",
			"teo": "",
			"horaInicioVaciado": "",
			"horaFinVaciado": "",
			"estado": "1",
			"cantAjuste": "0.00",
			"tipo": "MIXER",
			"volumenTotal": "8.00",
			"tipoPedido": "CONCRETO",
			"disenho": "1350N67B",
			"frecuencia": "60.00",
			"latitud": 0,
			"longitud": 0
		  }
		],
		"volumenTotal": "",
		"tipoPedido": "",
		"disenho": "",
		"frecuencia": "",
		"volumenAvance": "",
		"totalTiquete": "",
		"numeroTiquete": ""
	  },
	  {
		"idMarca": "1",
		"acuerdo": "208589",
		"fecha": 1552280400000,
		"codigoCliente": "003115",
		"codigoObra": "NA89",
		"obra": "CENTRO COMERCIAL COMAS - OBRA GRUESA",
		"pedido": "134",
		"direccion": "AVE LOS ANGELES CDRA 7 CON CALLE 5 s/n - COMAS / MG-251119-AV. LOS ANGELES CON CALLE CINCO FRENTE A UNICACHI",
		"horaInicio": "09:00",
		"estado": "COMPLETADO",
		"despachos": [
		  {
			"codigo": "13",
			"camion": "456",
			"elemento": "Losa",
			"planta": "Planta Collique",
			"plantaCodigo": "PCO",
			"guia": "117-0168538",
			"volumen": "8.00",
			"horaSalida": "08:54",
			"horaLlegada": "09:04",
			"teo": "38.00",
			"horaInicioVaciado": "09:42",
			"horaFinVaciado": "10:01",
			"estado": "5",
			"cantAjuste": "37.00",
			"tipo": "MIXER",
			"volumenTotal": "37.00",
			"tipoPedido": "CONCRETO",
			"disenho": "1280N67B",
			"frecuencia": "20.00",
			"latitud": 0,
			"longitud": 0
		  },
		  {
			"codigo": "14",
			"camion": "525",
			"elemento": "Losa",
			"planta": "Planta Collique",
			"plantaCodigo": "PCO",
			"guia": "117-0168539",
			"volumen": "8.00",
			"horaSalida": "09:09",
			"horaLlegada": "09:19",
			"teo": "37.00",
			"horaInicioVaciado": "09:56",
			"horaFinVaciado": "10:15",
			"estado": "5",
			"cantAjuste": "37.00",
			"tipo": "MIXER",
			"volumenTotal": "37.00",
			"tipoPedido": "CONCRETO",
			"disenho": "1280N67B",
			"frecuencia": "20.00",
			"latitud": 0,
			"longitud": 0
		  },
		  {
			"codigo": "15",
			"camion": "500",
			"elemento": "Losa",
			"planta": "Planta Collique",
			"plantaCodigo": "PCO",
			"guia": "117-0168540",
			"volumen": "8.00",
			"horaSalida": "09:31",
			"horaLlegada": "09:41",
			"teo": "35.00",
			"horaInicioVaciado": "10:16",
			"horaFinVaciado": "10:26",
			"estado": "5",
			"cantAjuste": "37.00",
			"tipo": "MIXER",
			"volumenTotal": "37.00",
			"tipoPedido": "CONCRETO",
			"disenho": "1280N67B",
			"frecuencia": "20.00",
			"latitud": 0,
			"longitud": 0
		  },
		  {
			"codigo": "16",
			"camion": "388",
			"elemento": "Losa",
			"planta": "Planta Collique",
			"plantaCodigo": "PCO",
			"guia": "117-0168542",
			"volumen": "7.00",
			"horaSalida": "09:57",
			"horaLlegada": "10:12",
			"teo": "24.00",
			"horaInicioVaciado": "10:36",
			"horaFinVaciado": "",
			"estado": "4",
			"cantAjuste": "37.00",
			"tipo": "MIXER",
			"volumenTotal": "37.00",
			"tipoPedido": "CONCRETO",
			"disenho": "1280N67B",
			"frecuencia": "20.00",
			"latitud": -11.9355766667,
			"longitud": -77.06427
		  },
		  {
			"codigo": "17",
			"camion": "262",
			"elemento": "Losa",
			"planta": "Planta Collique",
			"plantaCodigo": "PCO",
			"guia": "117-0168543",
			"volumen": "6.00",
			"horaSalida": "10:20",
			"horaLlegada": "10:37",
			"teo": "8.00",
			"horaInicioVaciado": "",
			"horaFinVaciado": "",
			"estado": "3",
			"cantAjuste": "37.00",
			"tipo": "MIXER",
			"volumenTotal": "37.00",
			"tipoPedido": "CONCRETO",
			"disenho": "1280N67B",
			"frecuencia": "20.00",
			"latitud": -11.9355166667,
			"longitud": -77.0644383333
		  }
		],
		"volumenTotal": "",
		"tipoPedido": "",
		"disenho": "",
		"frecuencia": "",
		"volumenAvance": "",
		"totalTiquete": "",
		"numeroTiquete": ""
	  },
	  {
		"idMarca": "1",
		"acuerdo": "208589",
		"fecha": 1552280400000,
		"codigoCliente": "003115",
		"codigoObra": "NA89",
		"obra": "CENTRO COMERCIAL COMAS - OBRA GRUESA",
		"pedido": "135",
		"direccion": "AVE LOS ANGELES CDRA 7 CON CALLE 5 s/n - COMAS / MG-251119-AV. LOS ANGELES CON CALLE CINCO FRENTE A UNICACHI",
		"horaInicio": "10:00",
		"estado": "EN ATENCIÓN",
		"despachos": [
		  {
			"codigo": "22",
			"camion": "433",
			"elemento": "Losa",
			"planta": "Planta Collique 2",
			"plantaCodigo": "PCL",
			"guia": "345-0000551",
			"volumen": "8.00",
			"horaSalida": "09:43",
			"horaLlegada": "09:53",
			"teo": "40.00",
			"horaInicioVaciado": "10:33",
			"horaFinVaciado": "",
			"estado": "4",
			"cantAjuste": "0.00",
			"tipo": "MIXER",
			"volumenTotal": "76.00",
			"tipoPedido": "CONCRETO",
			"disenho": "1280N67B",
			"frecuencia": "20.00",
			"latitud": -11.9362033333,
			"longitud": -77.06401
		  },
		  {
			"codigo": "23",
			"camion": "517",
			"elemento": "Losa",
			"planta": "Planta Collique 2",
			"plantaCodigo": "PCL",
			"guia": "345-0000552",
			"volumen": "7.00",
			"horaSalida": "10:13",
			"horaLlegada": "10:24",
			"teo": "21.00",
			"horaInicioVaciado": "",
			"horaFinVaciado": "",
			"estado": "3",
			"cantAjuste": "0.00",
			"tipo": "MIXER",
			"volumenTotal": "76.00",
			"tipoPedido": "CONCRETO",
			"disenho": "1280N67B",
			"frecuencia": "20.00",
			"latitud": -11.9358366667,
			"longitud": -77.063935
		  },
		  {
			"codigo": "24",
			"camion": "479",
			"elemento": "Losa",
			"planta": "Planta Collique 2",
			"plantaCodigo": "PCL",
			"guia": "345-0000553",
			"volumen": "8.00",
			"horaSalida": "10:26",
			"horaLlegada": "10:39",
			"teo": "6.00",
			"horaInicioVaciado": "",
			"horaFinVaciado": "",
			"estado": "3",
			"cantAjuste": "0.00",
			"tipo": "MIXER",
			"volumenTotal": "76.00",
			"tipoPedido": "CONCRETO",
			"disenho": "1280N67B",
			"frecuencia": "20.00",
			"latitud": -11.93576,
			"longitud": -77.063935
		  },
		  {
			"codigo": "25",
			"camion": "228",
			"elemento": "Losa",
			"planta": "Planta Collique 2",
			"plantaCodigo": "PCL",
			"guia": "345-0000554",
			"volumen": "7.00",
			"horaSalida": "",
			"horaLlegada": "",
			"teo": "0.00",
			"horaInicioVaciado": "",
			"horaFinVaciado": "",
			"estado": "1",
			"cantAjuste": "0.00",
			"tipo": "MIXER",
			"volumenTotal": "76.00",
			"tipoPedido": "CONCRETO",
			"disenho": "1280N67B",
			"frecuencia": "20.00",
			"latitud": 0,
			"longitud": 0
		  },
		  {
			"codigo": "26",
			"camion": "383",
			"elemento": "Losa",
			"planta": "Planta Collique 2",
			"plantaCodigo": "PCL",
			"guia": "345-0000555",
			"volumen": "7.00",
			"horaSalida": "",
			"horaLlegada": "",
			"teo": "0.00",
			"horaInicioVaciado": "",
			"horaFinVaciado": "",
			"estado": "1",
			"cantAjuste": "0.00",
			"tipo": "MIXER",
			"volumenTotal": "76.00",
			"tipoPedido": "CONCRETO",
			"disenho": "1280N67B",
			"frecuencia": "20.00",
			"latitud": 0,
			"longitud": 0
		  },
		  {
			"codigo": "27",
			"camion": "",
			"elemento": "Losa",
			"planta": "",
			"plantaCodigo": "",
			"guia": "",
			"volumen": "7.00",
			"horaSalida": "",
			"horaLlegada": "",
			"teo": "",
			"horaInicioVaciado": "",
			"horaFinVaciado": "",
			"estado": "1",
			"cantAjuste": "0.00",
			"tipo": "MIXER",
			"volumenTotal": "76.00",
			"tipoPedido": "CONCRETO",
			"disenho": "1280N67B",
			"frecuencia": "20.00",
			"latitud": 0,
			"longitud": 0
		  },
		  {
			"codigo": "28",
			"camion": "",
			"elemento": "Losa",
			"planta": "",
			"plantaCodigo": "",
			"guia": "",
			"volumen": "8.00",
			"horaSalida": "",
			"horaLlegada": "",
			"teo": "",
			"horaInicioVaciado": "",
			"horaFinVaciado": "",
			"estado": "1",
			"cantAjuste": "0.00",
			"tipo": "MIXER",
			"volumenTotal": "76.00",
			"tipoPedido": "CONCRETO",
			"disenho": "1280N67B",
			"frecuencia": "20.00",
			"latitud": 0,
			"longitud": 0
		  },
		  {
			"codigo": "29",
			"camion": "",
			"elemento": "Losa",
			"planta": "",
			"plantaCodigo": "",
			"guia": "",
			"volumen": "8.00",
			"horaSalida": "",
			"horaLlegada": "",
			"teo": "",
			"horaInicioVaciado": "",
			"horaFinVaciado": "",
			"estado": "1",
			"cantAjuste": "0.00",
			"tipo": "MIXER",
			"volumenTotal": "76.00",
			"tipoPedido": "CONCRETO",
			"disenho": "1280N67B",
			"frecuencia": "20.00",
			"latitud": 0,
			"longitud": 0
		  },
		  {
			"codigo": "30",
			"camion": "",
			"elemento": "Losa",
			"planta": "",
			"plantaCodigo": "",
			"guia": "",
			"volumen": "8.00",
			"horaSalida": "",
			"horaLlegada": "",
			"teo": "",
			"horaInicioVaciado": "",
			"horaFinVaciado": "",
			"estado": "1",
			"cantAjuste": "0.00",
			"tipo": "MIXER",
			"volumenTotal": "76.00",
			"tipoPedido": "CONCRETO",
			"disenho": "1280N67B",
			"frecuencia": "20.00",
			"latitud": 0,
			"longitud": 0
		  },
		  {
			"codigo": "31",
			"camion": "",
			"elemento": "Losa",
			"planta": "",
			"plantaCodigo": "",
			"guia": "",
			"volumen": "8.00",
			"horaSalida": "",
			"horaLlegada": "",
			"teo": "",
			"horaInicioVaciado": "",
			"horaFinVaciado": "",
			"estado": "1",
			"cantAjuste": "0.00",
			"tipo": "MIXER",
			"volumenTotal": "76.00",
			"tipoPedido": "CONCRETO",
			"disenho": "1280N67B",
			"frecuencia": "20.00",
			"latitud": 0,
			"longitud": 0
		  }
		],
		"volumenTotal": "",
		"tipoPedido": "",
		"disenho": "",
		"frecuencia": "",
		"volumenAvance": "",
		"totalTiquete": "",
		"numeroTiquete": ""
	  },
	  {
		"idMarca": "1",
		"acuerdo": "208589",
		"fecha": 1552280400000,
		"codigoCliente": "003115",
		"codigoObra": "NA89",
		"obra": "CENTRO COMERCIAL COMAS - OBRA GRUESA",
		"pedido": "136",
		"direccion": "AVE LOS ANGELES CDRA 7 CON CALLE 5 s/n - COMAS / MG-251119-AV. LOS ANGELES CON CALLE CINCO FRENTE A UNICACHI",
		"horaInicio": "13:00",
		"estado": "CONFIRMADO",
		"despachos": [
		  {
			"codigo": "32",
			"camion": "",
			"elemento": "Muros",
			"planta": "",
			"plantaCodigo": "",
			"guia": "",
			"volumen": "8.00",
			"horaSalida": "",
			"horaLlegada": "",
			"teo": "",
			"horaInicioVaciado": "",
			"horaFinVaciado": "",
			"estado": "1",
			"cantAjuste": "0.00",
			"tipo": "MIXER",
			"volumenTotal": "20.00",
			"tipoPedido": "CONCRETO",
			"disenho": "1280N67B",
			"frecuencia": "40.00",
			"latitud": 0,
			"longitud": 0
		  },
		  {
			"codigo": "33",
			"camion": "",
			"elemento": "Muros",
			"planta": "",
			"plantaCodigo": "",
			"guia": "",
			"volumen": "8.00",
			"horaSalida": "",
			"horaLlegada": "",
			"teo": "",
			"horaInicioVaciado": "",
			"horaFinVaciado": "",
			"estado": "1",
			"cantAjuste": "0.00",
			"tipo": "MIXER",
			"volumenTotal": "20.00",
			"tipoPedido": "CONCRETO",
			"disenho": "1280N67B",
			"frecuencia": "40.00",
			"latitud": 0,
			"longitud": 0
		  },
		  {
			"codigo": "34",
			"camion": "",
			"elemento": "Muros",
			"planta": "",
			"plantaCodigo": "",
			"guia": "",
			"volumen": "4.00",
			"horaSalida": "",
			"horaLlegada": "",
			"teo": "",
			"horaInicioVaciado": "",
			"horaFinVaciado": "",
			"estado": "1",
			"cantAjuste": "0.00",
			"tipo": "MIXER",
			"volumenTotal": "20.00",
			"tipoPedido": "CONCRETO",
			"disenho": "1280N67B",
			"frecuencia": "40.00",
			"latitud": 0,
			"longitud": 0
		  }
		],
		"volumenTotal": "",
		"tipoPedido": "",
		"disenho": "",
		"frecuencia": "",
		"volumenAvance": "",
		"totalTiquete": "",
		"numeroTiquete": ""
	  },
	  {
		"idMarca": "1",
		"acuerdo": "208589",
		"fecha": 1552280400000,
		"codigoCliente": "003115",
		"codigoObra": "NA89",
		"obra": "CENTRO COMERCIAL COMAS - OBRA GRUESA",
		"pedido": "137",
		"direccion": "AVE LOS ANGELES CDRA 7 CON CALLE 5 s/n - COMAS / MG-251119-AV. LOS ANGELES CON CALLE CINCO FRENTE A UNICACHI",
		"horaInicio": "13:00",
		"estado": "CONFIRMADO",
		"despachos": [
		  {
			"codigo": "35",
			"camion": "",
			"elemento": "Losa",
			"planta": "",
			"plantaCodigo": "",
			"guia": "",
			"volumen": "8.00",
			"horaSalida": "",
			"horaLlegada": "",
			"teo": "",
			"horaInicioVaciado": "",
			"horaFinVaciado": "",
			"estado": "1",
			"cantAjuste": "0.00",
			"tipo": "MIXER",
			"volumenTotal": "20.00",
			"tipoPedido": "CONCRETO",
			"disenho": "1280N67B",
			"frecuencia": "20.00",
			"latitud": 0,
			"longitud": 0
		  },
		  {
			"codigo": "36",
			"camion": "",
			"elemento": "Losa",
			"planta": "",
			"plantaCodigo": "",
			"guia": "",
			"volumen": "8.00",
			"horaSalida": "",
			"horaLlegada": "",
			"teo": "",
			"horaInicioVaciado": "",
			"horaFinVaciado": "",
			"estado": "1",
			"cantAjuste": "0.00",
			"tipo": "MIXER",
			"volumenTotal": "20.00",
			"tipoPedido": "CONCRETO",
			"disenho": "1280N67B",
			"frecuencia": "20.00",
			"latitud": 0,
			"longitud": 0
		  },
		  {
			"codigo": "37",
			"camion": "",
			"elemento": "Losa",
			"planta": "",
			"plantaCodigo": "",
			"guia": "",
			"volumen": "4.00",
			"horaSalida": "",
			"horaLlegada": "",
			"teo": "",
			"horaInicioVaciado": "",
			"horaFinVaciado": "",
			"estado": "1",
			"cantAjuste": "0.00",
			"tipo": "MIXER",
			"volumenTotal": "20.00",
			"tipoPedido": "CONCRETO",
			"disenho": "1280N67B",
			"frecuencia": "20.00",
			"latitud": 0,
			"longitud": 0
		  }
		],
		"volumenTotal": "",
		"tipoPedido": "",
		"disenho": "",
		"frecuencia": "",
		"volumenAvance": "",
		"totalTiquete": "",
		"numeroTiquete": ""
	  },
	  {
		"idMarca": "1",
		"acuerdo": "208589",
		"fecha": 1552280400000,
		"codigoCliente": "003115",
		"codigoObra": "NA89",
		"obra": "CENTRO COMERCIAL COMAS - OBRA GRUESA",
		"pedido": "138",
		"direccion": "AVE LOS ANGELES CDRA 7 CON CALLE 5 s/n - COMAS / MG-251119-AV. LOS ANGELES CON CALLE CINCO FRENTE A UNICACHI",
		"horaInicio": "08:15",
		"estado": "CONFIRMADO",
		"despachos": [
		  {
			"codigo": "38",
			"camion": "",
			"elemento": "Losa",
			"planta": "",
			"plantaCodigo": "",
			"guia": "",
			"volumen": "8.00",
			"horaSalida": "",
			"horaLlegada": "",
			"teo": "",
			"horaInicioVaciado": "",
			"horaFinVaciado": "",
			"estado": "1",
			"cantAjuste": "0.00",
			"tipo": "MIXER",
			"volumenTotal": "50.00",
			"tipoPedido": "CONCRETO",
			"disenho": "1280N67B",
			"frecuencia": "20.00",
			"latitud": 0,
			"longitud": 0
		  },
		  {
			"codigo": "39",
			"camion": "",
			"elemento": "Losa",
			"planta": "",
			"plantaCodigo": "",
			"guia": "",
			"volumen": "8.00",
			"horaSalida": "",
			"horaLlegada": "",
			"teo": "",
			"horaInicioVaciado": "",
			"horaFinVaciado": "",
			"estado": "1",
			"cantAjuste": "0.00",
			"tipo": "MIXER",
			"volumenTotal": "50.00",
			"tipoPedido": "CONCRETO",
			"disenho": "1280N67B",
			"frecuencia": "20.00",
			"latitud": 0,
			"longitud": 0
		  },
		  {
			"codigo": "40",
			"camion": "",
			"elemento": "Losa",
			"planta": "",
			"plantaCodigo": "",
			"guia": "",
			"volumen": "8.00",
			"horaSalida": "",
			"horaLlegada": "",
			"teo": "",
			"horaInicioVaciado": "",
			"horaFinVaciado": "",
			"estado": "1",
			"cantAjuste": "0.00",
			"tipo": "MIXER",
			"volumenTotal": "50.00",
			"tipoPedido": "CONCRETO",
			"disenho": "1280N67B",
			"frecuencia": "20.00",
			"latitud": 0,
			"longitud": 0
		  },
		  {
			"codigo": "41",
			"camion": "",
			"elemento": "Losa",
			"planta": "",
			"plantaCodigo": "",
			"guia": "",
			"volumen": "8.00",
			"horaSalida": "",
			"horaLlegada": "",
			"teo": "",
			"horaInicioVaciado": "",
			"horaFinVaciado": "",
			"estado": "1",
			"cantAjuste": "0.00",
			"tipo": "MIXER",
			"volumenTotal": "50.00",
			"tipoPedido": "CONCRETO",
			"disenho": "1280N67B",
			"frecuencia": "20.00",
			"latitud": 0,
			"longitud": 0
		  },
		  {
			"codigo": "42",
			"camion": "",
			"elemento": "Losa",
			"planta": "",
			"plantaCodigo": "",
			"guia": "",
			"volumen": "8.00",
			"horaSalida": "",
			"horaLlegada": "",
			"teo": "",
			"horaInicioVaciado": "",
			"horaFinVaciado": "",
			"estado": "1",
			"cantAjuste": "0.00",
			"tipo": "MIXER",
			"volumenTotal": "50.00",
			"tipoPedido": "CONCRETO",
			"disenho": "1280N67B",
			"frecuencia": "20.00",
			"latitud": 0,
			"longitud": 0
		  },
		  {
			"codigo": "43",
			"camion": "",
			"elemento": "Losa",
			"planta": "",
			"plantaCodigo": "",
			"guia": "",
			"volumen": "7.00",
			"horaSalida": "",
			"horaLlegada": "",
			"teo": "",
			"horaInicioVaciado": "",
			"horaFinVaciado": "",
			"estado": "1",
			"cantAjuste": "0.00",
			"tipo": "MIXER",
			"volumenTotal": "50.00",
			"tipoPedido": "CONCRETO",
			"disenho": "1280N67B",
			"frecuencia": "20.00",
			"latitud": 0,
			"longitud": 0
		  },
		  {
			"codigo": "44",
			"camion": "",
			"elemento": "Losa",
			"planta": "",
			"plantaCodigo": "",
			"guia": "",
			"volumen": "3.00",
			"horaSalida": "",
			"horaLlegada": "",
			"teo": "",
			"horaInicioVaciado": "",
			"horaFinVaciado": "",
			"estado": "1",
			"cantAjuste": "0.00",
			"tipo": "MIXER",
			"volumenTotal": "50.00",
			"tipoPedido": "CONCRETO",
			"disenho": "1280N67B",
			"frecuencia": "20.00",
			"latitud": 0,
			"longitud": 0
		  }
		],
		"volumenTotal": "",
		"tipoPedido": "",
		"disenho": "",
		"frecuencia": "",
		"volumenAvance": "",
		"totalTiquete": "",
		"numeroTiquete": ""
	  },
	  {
		"idMarca": "1",
		"acuerdo": "208589",
		"fecha": 1552280400000,
		"codigoCliente": "003115",
		"codigoObra": "NA89",
		"obra": "CENTRO COMERCIAL COMAS - OBRA GRUESA",
		"pedido": "510",
		"direccion": "AVE LOS ANGELES CDRA 7 CON CALLE 5 S/N s/n - COMAS / MG-251119-AV. LOS ANGELES CON CALLE CINCO FRENTE A UNICACHI",
		"horaInicio": "15:00",
		"estado": "CONFIRMADO",
		"despachos": [
		  {
			"codigo": "84",
			"camion": "",
			"elemento": "Columna",
			"planta": "",
			"plantaCodigo": "",
			"guia": "",
			"volumen": "8.00",
			"horaSalida": "",
			"horaLlegada": "",
			"teo": "",
			"horaInicioVaciado": "",
			"horaFinVaciado": "",
			"estado": "1",
			"cantAjuste": "0.00",
			"tipo": "MIXER",
			"volumenTotal": "20.00",
			"tipoPedido": "CONCRETO",
			"disenho": "1280N67B",
			"frecuencia": "45.00",
			"latitud": 0,
			"longitud": 0
		  },
		  {
			"codigo": "85",
			"camion": "",
			"elemento": "Columna",
			"planta": "",
			"plantaCodigo": "",
			"guia": "",
			"volumen": "8.00",
			"horaSalida": "",
			"horaLlegada": "",
			"teo": "",
			"horaInicioVaciado": "",
			"horaFinVaciado": "",
			"estado": "1",
			"cantAjuste": "0.00",
			"tipo": "MIXER",
			"volumenTotal": "20.00",
			"tipoPedido": "CONCRETO",
			"disenho": "1280N67B",
			"frecuencia": "45.00",
			"latitud": 0,
			"longitud": 0
		  },
		  {
			"codigo": "86",
			"camion": "",
			"elemento": "Columna",
			"planta": "",
			"plantaCodigo": "",
			"guia": "",
			"volumen": "4.00",
			"horaSalida": "",
			"horaLlegada": "",
			"teo": "",
			"horaInicioVaciado": "",
			"horaFinVaciado": "",
			"estado": "1",
			"cantAjuste": "0.00",
			"tipo": "MIXER",
			"volumenTotal": "20.00",
			"tipoPedido": "CONCRETO",
			"disenho": "1280N67B",
			"frecuencia": "45.00",
			"latitud": 0,
			"longitud": 0
		  }
		],
		"volumenTotal": "",
		"tipoPedido": "",
		"disenho": "",
		"frecuencia": "",
		"volumenAvance": "",
		"totalTiquete": "",
		"numeroTiquete": ""
	  },
	  {
		"idMarca": "1",
		"acuerdo": "208589",
		"fecha": 1552280400000,
		"codigoCliente": "003115",
		"codigoObra": "NA89",
		"obra": "CENTRO COMERCIAL COMAS - OBRA GRUESA",
		"pedido": "511",
		"direccion": "AVE LOS ANGELES CDRA 7 CON CALLE 5 S/N s/n - COMAS / MG-251119-AV. LOS ANGELES CON CALLE CINCO FRENTE A UNICACHI",
		"horaInicio": "13:00",
		"estado": "CONFIRMADO",
		"despachos": [
		  {
			"codigo": "87",
			"camion": "",
			"elemento": "Columna",
			"planta": "",
			"plantaCodigo": "",
			"guia": "",
			"volumen": "8.00",
			"horaSalida": "",
			"horaLlegada": "",
			"teo": "",
			"horaInicioVaciado": "",
			"horaFinVaciado": "",
			"estado": "1",
			"cantAjuste": "0.00",
			"tipo": "MIXER",
			"volumenTotal": "20.00",
			"tipoPedido": "CONCRETO",
			"disenho": "1280N67B",
			"frecuencia": "45.00",
			"latitud": 0,
			"longitud": 0
		  },
		  {
			"codigo": "88",
			"camion": "",
			"elemento": "Columna",
			"planta": "",
			"plantaCodigo": "",
			"guia": "",
			"volumen": "8.00",
			"horaSalida": "",
			"horaLlegada": "",
			"teo": "",
			"horaInicioVaciado": "",
			"horaFinVaciado": "",
			"estado": "1",
			"cantAjuste": "0.00",
			"tipo": "MIXER",
			"volumenTotal": "20.00",
			"tipoPedido": "CONCRETO",
			"disenho": "1280N67B",
			"frecuencia": "45.00",
			"latitud": 0,
			"longitud": 0
		  },
		  {
			"codigo": "89",
			"camion": "",
			"elemento": "Columna",
			"planta": "",
			"plantaCodigo": "",
			"guia": "",
			"volumen": "4.00",
			"horaSalida": "",
			"horaLlegada": "",
			"teo": "",
			"horaInicioVaciado": "",
			"horaFinVaciado": "",
			"estado": "1",
			"cantAjuste": "0.00",
			"tipo": "MIXER",
			"volumenTotal": "20.00",
			"tipoPedido": "CONCRETO",
			"disenho": "1280N67B",
			"frecuencia": "45.00",
			"latitud": 0,
			"longitud": 0
		  }
		],
		"volumenTotal": "",
		"tipoPedido": "",
		"disenho": "",
		"frecuencia": "",
		"volumenAvance": "",
		"totalTiquete": "",
		"numeroTiquete": ""
	  },
	  {
		"idMarca": "1",
		"acuerdo": "209189",
		"fecha": 1552280400000,
		"codigoCliente": "003115",
		"codigoObra": "GY62",
		"obra": "SHOPPING LA MOLINA ETAPA 1",
		"pedido": "85",
		"direccion": "CAL LOS  ACEBOS CON CALLE LOS BAMBUES S/N - LA MOLINA / MG-300319-",
		"horaInicio": "09:30",
		"estado": "COMPLETADO",
		"despachos": [
		  {
			"codigo": "7",
			"camion": "219",
			"elemento": "Losa",
			"planta": "ANCIETA 4",
			"plantaCodigo": "AN4",
			"guia": "338-0021818",
			"volumen": "6.00",
			"horaSalida": "08:55",
			"horaLlegada": "09:54",
			"teo": "26.00",
			"horaInicioVaciado": "10:20",
			"horaFinVaciado": "",
			"estado": "4",
			"cantAjuste": "18.50",
			"tipo": "MIXER",
			"volumenTotal": "18.50",
			"tipoPedido": "CONCRETO",
			"disenho": "1280N67C",
			"frecuencia": "30.00",
			"latitud": -12.0917816667,
			"longitud": -76.9511266667
		  },
		  {
			"codigo": "9",
			"camion": "230",
			"elemento": "Losa",
			"planta": "Planta Ancieta",
			"plantaCodigo": "ANC",
			"guia": "009-0490451",
			"volumen": "5.50",
			"horaSalida": "09:56",
			"horaLlegada": "10:43",
			"teo": "2.00",
			"horaInicioVaciado": "",
			"horaFinVaciado": "",
			"estado": "3",
			"cantAjuste": "18.50",
			"tipo": "MIXER",
			"volumenTotal": "18.50",
			"tipoPedido": "CONCRETO",
			"disenho": "1280N67C",
			"frecuencia": "30.00",
			"latitud": -12.091385,
			"longitud": -76.952195
		  },
		  {
			"codigo": "8",
			"camion": "653",
			"elemento": "Losa",
			"planta": "Planta Ancieta",
			"plantaCodigo": "ANC",
			"guia": "009-0490448",
			"volumen": "7.00",
			"horaSalida": "09:18",
			"horaLlegada": "09:59 (Estimado)",
			"teo": "0.00",
			"horaInicioVaciado": "",
			"horaFinVaciado": "",
			"estado": "2",
			"cantAjuste": "18.50",
			"tipo": "MIXER",
			"volumenTotal": "18.50",
			"tipoPedido": "CONCRETO",
			"disenho": "1280N67C",
			"frecuencia": "30.00",
			"latitud": -12.09166,
			"longitud": -76.9511416667
		  }
		],
		"volumenTotal": "",
		"tipoPedido": "",
		"disenho": "",
		"frecuencia": "",
		"volumenAvance": "",
		"totalTiquete": "",
		"numeroTiquete": ""
	  },
	  {
		"idMarca": "1",
		"acuerdo": "209189",
		"fecha": 1552280400000,
		"codigoCliente": "003115",
		"codigoObra": "GY62",
		"obra": "SHOPPING LA MOLINA ETAPA 1",
		"pedido": "391",
		"direccion": "CAL LOS  ACEBOS CON CALLE LOS BAMBUES S/N - LA MOLINA / MG-300319-",
		"horaInicio": "09:45",
		"estado": "COMPLETADO",
		"despachos": [
		  {
			"codigo": "68",
			"camion": "443",
			"elemento": "Losa",
			"planta": "Planta Ancieta 2",
			"plantaCodigo": "AN3",
			"guia": "141-0150728",
			"volumen": "7.00",
			"horaSalida": "08:56",
			"horaLlegada": "10:10",
			"teo": "35.00",
			"horaInicioVaciado": "",
			"horaFinVaciado": "",
			"estado": "3",
			"cantAjuste": "14.00",
			"tipo": "MIXER",
			"volumenTotal": "14.00",
			"tipoPedido": "CONCRETO",
			"disenho": "1280N67C",
			"frecuencia": "30.00",
			"latitud": -12.091675,
			"longitud": -76.9511416667
		  },
		  {
			"codigo": "69",
			"camion": "442",
			"elemento": "Losa",
			"planta": "Planta Ancieta",
			"plantaCodigo": "ANC",
			"guia": "009-0490449",
			"volumen": "7.00",
			"horaSalida": "09:36",
			"horaLlegada": "10:15",
			"teo": "30.00",
			"horaInicioVaciado": "",
			"horaFinVaciado": "",
			"estado": "3",
			"cantAjuste": "14.00",
			"tipo": "MIXER",
			"volumenTotal": "14.00",
			"tipoPedido": "CONCRETO",
			"disenho": "1280N67C",
			"frecuencia": "30.00",
			"latitud": -12.0915066667,
			"longitud": -76.9520116667
		  }
		],
		"volumenTotal": "",
		"tipoPedido": "",
		"disenho": "",
		"frecuencia": "",
		"volumenAvance": "",
		"totalTiquete": "",
		"numeroTiquete": ""
	  },
	  {
		"idMarca": "1",
		"acuerdo": "209189",
		"fecha": 1552280400000,
		"codigoCliente": "003115",
		"codigoObra": "GY62",
		"obra": "SHOPPING LA MOLINA ETAPA 1",
		"pedido": "393",
		"direccion": "CAL LOS  ACEBOS CON CALLE LOS BAMBUES S/N - LA MOLINA / MG-300319-",
		"horaInicio": "14:00",
		"estado": "CONFIRMADO",
		"despachos": [
		  {
			"codigo": "73",
			"camion": "",
			"elemento": "Muros",
			"planta": "",
			"plantaCodigo": "",
			"guia": "",
			"volumen": "3.00",
			"horaSalida": "",
			"horaLlegada": "",
			"teo": "",
			"horaInicioVaciado": "",
			"horaFinVaciado": "",
			"estado": "1",
			"cantAjuste": "3.00",
			"tipo": "MIXER",
			"volumenTotal": "3.00",
			"tipoPedido": "CONCRETO",
			"disenho": "1280N67C",
			"frecuencia": "30.00",
			"latitud": 0,
			"longitud": 0
		  }
		],
		"volumenTotal": "",
		"tipoPedido": "",
		"disenho": "",
		"frecuencia": "",
		"volumenAvance": "",
		"totalTiquete": "",
		"numeroTiquete": ""
	  },
	  {
		"idMarca": "1",
		"acuerdo": "209189",
		"fecha": 1552280400000,
		"codigoCliente": "003115",
		"codigoObra": "GY62",
		"obra": "SHOPPING LA MOLINA ETAPA 1",
		"pedido": "395",
		"direccion": "CAL LOS  ACEBOS CON CALLE LOS BAMBUES S/N - LA MOLINA / MG-300319-",
		"horaInicio": "13:15",
		"estado": "CONFIRMADO",
		"despachos": [
		  {
			"codigo": "77",
			"camion": "",
			"elemento": "Muros",
			"planta": "",
			"plantaCodigo": "",
			"guia": "",
			"volumen": "6.00",
			"horaSalida": "",
			"horaLlegada": "",
			"teo": "",
			"horaInicioVaciado": "",
			"horaFinVaciado": "",
			"estado": "1",
			"cantAjuste": "0.00",
			"tipo": "MIXER",
			"volumenTotal": "15.00",
			"tipoPedido": "CONCRETO",
			"disenho": "1280N67C",
			"frecuencia": "30.00",
			"latitud": 0,
			"longitud": 0
		  },
		  {
			"codigo": "78",
			"camion": "",
			"elemento": "Muros",
			"planta": "",
			"plantaCodigo": "",
			"guia": "",
			"volumen": "6.00",
			"horaSalida": "",
			"horaLlegada": "",
			"teo": "",
			"horaInicioVaciado": "",
			"horaFinVaciado": "",
			"estado": "1",
			"cantAjuste": "0.00",
			"tipo": "MIXER",
			"volumenTotal": "15.00",
			"tipoPedido": "CONCRETO",
			"disenho": "1280N67C",
			"frecuencia": "30.00",
			"latitud": 0,
			"longitud": 0
		  },
		  {
			"codigo": "79",
			"camion": "",
			"elemento": "Muros",
			"planta": "",
			"plantaCodigo": "",
			"guia": "",
			"volumen": "3.00",
			"horaSalida": "",
			"horaLlegada": "",
			"teo": "",
			"horaInicioVaciado": "",
			"horaFinVaciado": "",
			"estado": "1",
			"cantAjuste": "0.00",
			"tipo": "MIXER",
			"volumenTotal": "15.00",
			"tipoPedido": "CONCRETO",
			"disenho": "1280N67C",
			"frecuencia": "30.00",
			"latitud": 0,
			"longitud": 0
		  }
		],
		"volumenTotal": "",
		"tipoPedido": "",
		"disenho": "",
		"frecuencia": "",
		"volumenAvance": "",
		"totalTiquete": "",
		"numeroTiquete": ""
	  },
	  {
		"idMarca": "1",
		"acuerdo": "209189",
		"fecha": 1552280400000,
		"codigoCliente": "003115",
		"codigoObra": "GY62",
		"obra": "SHOPPING LA MOLINA ETAPA 1",
		"pedido": "404",
		"direccion": "CAL LOS  ACEBOS CON CALLE LOS BAMBUES S/N - LA MOLINA / MG-300319-",
		"horaInicio": "15:00",
		"estado": "CONFIRMADO",
		"despachos": [
		  {
			"codigo": "80",
			"camion": "",
			"elemento": "Muros",
			"planta": "",
			"plantaCodigo": "",
			"guia": "",
			"volumen": "7.00",
			"horaSalida": "",
			"horaLlegada": "",
			"teo": "",
			"horaInicioVaciado": "",
			"horaFinVaciado": "",
			"estado": "1",
			"cantAjuste": "0.00",
			"tipo": "MIXER",
			"volumenTotal": "7.00",
			"tipoPedido": "CONCRETO",
			"disenho": "1280N67C",
			"frecuencia": "60.00",
			"latitud": 0,
			"longitud": 0
		  }
		],
		"volumenTotal": "",
		"tipoPedido": "",
		"disenho": "",
		"frecuencia": "",
		"volumenAvance": "",
		"totalTiquete": "",
		"numeroTiquete": ""
	  },
	  {
		"idMarca": "1",
		"acuerdo": "209254",
		"fecha": 1552280400000,
		"codigoCliente": "003115",
		"codigoObra": "LB43",
		"obra": "PROYECTO EDIFICIO HARA",
		"pedido": "257",
		"direccion": "JIR FERMIN TANGUIS 160 SANTA CATALINA - LA VICTORIA / G-300519-PAOLO HUAMAN   944470362",
		"horaInicio": "14:00",
		"estado": "CONFIRMADO",
		"despachos": [
		  {
			"codigo": "60",
			"camion": "",
			"elemento": "Losa",
			"planta": "",
			"plantaCodigo": "",
			"guia": "",
			"volumen": "8.00",
			"horaSalida": "",
			"horaLlegada": "",
			"teo": "",
			"horaInicioVaciado": "",
			"horaFinVaciado": "",
			"estado": "1",
			"cantAjuste": "0.00",
			"tipo": "MIXER",
			"volumenTotal": "35.00",
			"tipoPedido": "CONCRETO Y SERVICIO DE BOMBA",
			"disenho": "1210N67B",
			"frecuencia": "35.00",
			"latitud": 0,
			"longitud": 0
		  },
		  {
			"codigo": "61",
			"camion": "",
			"elemento": "Losa",
			"planta": "",
			"plantaCodigo": "",
			"guia": "",
			"volumen": "8.00",
			"horaSalida": "",
			"horaLlegada": "",
			"teo": "",
			"horaInicioVaciado": "",
			"horaFinVaciado": "",
			"estado": "1",
			"cantAjuste": "0.00",
			"tipo": "MIXER",
			"volumenTotal": "35.00",
			"tipoPedido": "CONCRETO Y SERVICIO DE BOMBA",
			"disenho": "1210N67B",
			"frecuencia": "35.00",
			"latitud": 0,
			"longitud": 0
		  },
		  {
			"codigo": "62",
			"camion": "",
			"elemento": "Losa",
			"planta": "",
			"plantaCodigo": "",
			"guia": "",
			"volumen": "8.00",
			"horaSalida": "",
			"horaLlegada": "",
			"teo": "",
			"horaInicioVaciado": "",
			"horaFinVaciado": "",
			"estado": "1",
			"cantAjuste": "0.00",
			"tipo": "MIXER",
			"volumenTotal": "35.00",
			"tipoPedido": "CONCRETO Y SERVICIO DE BOMBA",
			"disenho": "1210N67B",
			"frecuencia": "35.00",
			"latitud": 0,
			"longitud": 0
		  },
		  {
			"codigo": "63",
			"camion": "",
			"elemento": "Losa",
			"planta": "",
			"plantaCodigo": "",
			"guia": "",
			"volumen": "8.00",
			"horaSalida": "",
			"horaLlegada": "",
			"teo": "",
			"horaInicioVaciado": "",
			"horaFinVaciado": "",
			"estado": "1",
			"cantAjuste": "0.00",
			"tipo": "MIXER",
			"volumenTotal": "35.00",
			"tipoPedido": "CONCRETO Y SERVICIO DE BOMBA",
			"disenho": "1210N67B",
			"frecuencia": "35.00",
			"latitud": 0,
			"longitud": 0
		  },
		  {
			"codigo": "64",
			"camion": "",
			"elemento": "Losa",
			"planta": "",
			"plantaCodigo": "",
			"guia": "",
			"volumen": "3.00",
			"horaSalida": "",
			"horaLlegada": "",
			"teo": "",
			"horaInicioVaciado": "",
			"horaFinVaciado": "",
			"estado": "1",
			"cantAjuste": "0.00",
			"tipo": "MIXER",
			"volumenTotal": "35.00",
			"tipoPedido": "CONCRETO Y SERVICIO DE BOMBA",
			"disenho": "1210N67B",
			"frecuencia": "35.00",
			"latitud": 0,
			"longitud": 0
		  },
		  {
			"codigo": "91",
			"camion": "",
			"elemento": "",
			"planta": "",
			"plantaCodigo": "",
			"guia": "",
			"volumen": "35.00",
			"horaSalida": "",
			"horaLlegada": "",
			"teo": "",
			"horaInicioVaciado": "",
			"horaFinVaciado": "",
			"estado": "1",
			"cantAjuste": "0.00",
			"tipo": "BOMBA",
			"volumenTotal": "35.00",
			"tipoPedido": "CONCRETO Y SERVICIO DE BOMBA",
			"disenho": "",
			"frecuencia": "0.00",
			"latitud": 0,
			"longitud": 0
		  }
		],
		"volumenTotal": "",
		"tipoPedido": "",
		"disenho": "",
		"frecuencia": "",
		"volumenAvance": "",
		"totalTiquete": "",
		"numeroTiquete": ""
	  },
	  {
		"idMarca": "1",
		"acuerdo": "209254",
		"fecha": 1552280400000,
		"codigoCliente": "003115",
		"codigoObra": "LB43",
		"obra": "PROYECTO EDIFICIO HARA",
		"pedido": "258",
		"direccion": "JIR FERMIN TANGUIS 160 SANTA CATALINA - LA VICTORIA / G-300519-PAOLO HUAMAN   944470362",
		"horaInicio": "17:10",
		"estado": "CONFIRMADO",
		"despachos": [
		  {
			"codigo": "65",
			"camion": "",
			"elemento": "Muros",
			"planta": "",
			"plantaCodigo": "",
			"guia": "",
			"volumen": "8.00",
			"horaSalida": "",
			"horaLlegada": "",
			"teo": "",
			"horaInicioVaciado": "",
			"horaFinVaciado": "",
			"estado": "1",
			"cantAjuste": "0.00",
			"tipo": "MIXER",
			"volumenTotal": "14.00",
			"tipoPedido": "CONCRETO Y SERVICIO DE BOMBA",
			"disenho": "1210N67B",
			"frecuencia": "25.00",
			"latitud": 0,
			"longitud": 0
		  },
		  {
			"codigo": "66",
			"camion": "",
			"elemento": "Muros",
			"planta": "",
			"plantaCodigo": "",
			"guia": "",
			"volumen": "6.00",
			"horaSalida": "",
			"horaLlegada": "",
			"teo": "",
			"horaInicioVaciado": "",
			"horaFinVaciado": "",
			"estado": "1",
			"cantAjuste": "0.00",
			"tipo": "MIXER",
			"volumenTotal": "14.00",
			"tipoPedido": "CONCRETO Y SERVICIO DE BOMBA",
			"disenho": "1210N67B",
			"frecuencia": "25.00",
			"latitud": 0,
			"longitud": 0
		  },
		  {
			"codigo": "92",
			"camion": "",
			"elemento": "",
			"planta": "",
			"plantaCodigo": "",
			"guia": "",
			"volumen": "14.00",
			"horaSalida": "",
			"horaLlegada": "",
			"teo": "",
			"horaInicioVaciado": "",
			"horaFinVaciado": "",
			"estado": "1",
			"cantAjuste": "0.00",
			"tipo": "BOMBA",
			"volumenTotal": "14.00",
			"tipoPedido": "CONCRETO Y SERVICIO DE BOMBA",
			"disenho": "",
			"frecuencia": "0.00",
			"latitud": 0,
			"longitud": 0
		  }
		],
		"volumenTotal": "",
		"tipoPedido": "",
		"disenho": "",
		"frecuencia": "",
		"volumenAvance": "",
		"totalTiquete": "",
		"numeroTiquete": ""
	  },
	  {
		"idMarca": "1",
		"acuerdo": "209254",
		"fecha": 1552280400000,
		"codigoCliente": "003115",
		"codigoObra": "LB43",
		"obra": "PROYECTO EDIFICIO HARA",
		"pedido": "419",
		"direccion": "JIR FERMIN TANGUIS 160 SANTA CATALINA - LA VICTORIA / G-300519-PAOLO HUAMAN   944470362",
		"horaInicio": "15:30",
		"estado": "CONFIRMADO",
		"despachos": [
		  {
			"codigo": "81",
			"camion": "",
			"elemento": "Columna",
			"planta": "",
			"plantaCodigo": "",
			"guia": "",
			"volumen": "5.00",
			"horaSalida": "",
			"horaLlegada": "",
			"teo": "",
			"horaInicioVaciado": "",
			"horaFinVaciado": "",
			"estado": "1",
			"cantAjuste": "0.00",
			"tipo": "MIXER",
			"volumenTotal": "5.00",
			"tipoPedido": "CONCRETO",
			"disenho": "1280N67B",
			"frecuencia": "25.00",
			"latitud": 0,
			"longitud": 0
		  }
		],
		"volumenTotal": "",
		"tipoPedido": "",
		"disenho": "",
		"frecuencia": "",
		"volumenAvance": "",
		"totalTiquete": "",
		"numeroTiquete": ""
	  },
	  {
		"idMarca": "1",
		"acuerdo": "209254",
		"fecha": 1552280400000,
		"codigoCliente": "003115",
		"codigoObra": "LB43",
		"obra": "PROYECTO EDIFICIO HARA",
		"pedido": "451",
		"direccion": "JIR FERMIN TANGUIS 160 SANTA CATALINA - LA VICTORIA / G-300519-PAOLO HUAMAN   944470362",
		"horaInicio": "16:00",
		"estado": "CONFIRMADO",
		"despachos": [
		  {
			"codigo": "82",
			"camion": "",
			"elemento": "Columna",
			"planta": "",
			"plantaCodigo": "",
			"guia": "",
			"volumen": "5.00",
			"horaSalida": "",
			"horaLlegada": "",
			"teo": "",
			"horaInicioVaciado": "",
			"horaFinVaciado": "",
			"estado": "1",
			"cantAjuste": "0.00",
			"tipo": "MIXER",
			"volumenTotal": "5.00",
			"tipoPedido": "CONCRETO",
			"disenho": "1350N57B",
			"frecuencia": "25.00",
			"latitud": 0,
			"longitud": 0
		  }
		],
		"volumenTotal": "",
		"tipoPedido": "",
		"disenho": "",
		"frecuencia": "",
		"volumenAvance": "",
		"totalTiquete": "",
		"numeroTiquete": ""
	  },
	  {
		"idMarca": "1",
		"acuerdo": "209254",
		"fecha": 1552280400000,
		"codigoCliente": "003115",
		"codigoObra": "LB43",
		"obra": "PROYECTO EDIFICIO HARA",
		"pedido": "460",
		"direccion": "JIR FERMIN TANGUIS 160 SANTA CATALINA - LA VICTORIA / G-300519-PAOLO HUAMAN   944470362",
		"horaInicio": "16:30",
		"estado": "CONFIRMADO",
		"despachos": [
		  {
			"codigo": "83",
			"camion": "",
			"elemento": "Columna",
			"planta": "",
			"plantaCodigo": "",
			"guia": "",
			"volumen": "5.00",
			"horaSalida": "",
			"horaLlegada": "",
			"teo": "",
			"horaInicioVaciado": "",
			"horaFinVaciado": "",
			"estado": "1",
			"cantAjuste": "0.00",
			"tipo": "MIXER",
			"volumenTotal": "5.00",
			"tipoPedido": "CONCRETO",
			"disenho": "1280N67B",
			"frecuencia": "25.00",
			"latitud": 0,
			"longitud": 0
		  }
		],
		"volumenTotal": "",
		"tipoPedido": "",
		"disenho": "",
		"frecuencia": "",
		"volumenAvance": "",
		"totalTiquete": "",
		"numeroTiquete": ""
	  },
	  {
		"idMarca": "1",
		"acuerdo": "209256",
		"fecha": 1552280400000,
		"codigoCliente": "003115",
		"codigoObra": "KR26",
		"obra": "EDIFICIO \"LAS CAMELIAS\"",
		"pedido": "187",
		"direccion": "CAL LAS CAMELIAS ESQ. AMADOR MERINO s/n - SAN ISIDRO / G-080419-san isidro",
		"horaInicio": "13:30",
		"estado": "CONFIRMADO",
		"despachos": [
		  {
			"codigo": "45",
			"camion": "",
			"elemento": "Muros",
			"planta": "",
			"plantaCodigo": "",
			"guia": "",
			"volumen": "8.00",
			"horaSalida": "",
			"horaLlegada": "",
			"teo": "",
			"horaInicioVaciado": "",
			"horaFinVaciado": "",
			"estado": "1",
			"cantAjuste": "0.00",
			"tipo": "MIXER",
			"volumenTotal": "17.00",
			"tipoPedido": "CONCRETO",
			"disenho": "1350N57B",
			"frecuencia": "40.00",
			"latitud": 0,
			"longitud": 0
		  },
		  {
			"codigo": "46",
			"camion": "",
			"elemento": "Muros",
			"planta": "",
			"plantaCodigo": "",
			"guia": "",
			"volumen": "5.00",
			"horaSalida": "",
			"horaLlegada": "",
			"teo": "",
			"horaInicioVaciado": "",
			"horaFinVaciado": "",
			"estado": "1",
			"cantAjuste": "0.00",
			"tipo": "MIXER",
			"volumenTotal": "17.00",
			"tipoPedido": "CONCRETO",
			"disenho": "1350N57B",
			"frecuencia": "40.00",
			"latitud": 0,
			"longitud": 0
		  },
		  {
			"codigo": "47",
			"camion": "",
			"elemento": "Muros",
			"planta": "",
			"plantaCodigo": "",
			"guia": "",
			"volumen": "4.00",
			"horaSalida": "",
			"horaLlegada": "",
			"teo": "",
			"horaInicioVaciado": "",
			"horaFinVaciado": "",
			"estado": "1",
			"cantAjuste": "0.00",
			"tipo": "MIXER",
			"volumenTotal": "17.00",
			"tipoPedido": "CONCRETO",
			"disenho": "1350N57B",
			"frecuencia": "40.00",
			"latitud": 0,
			"longitud": 0
		  }
		],
		"volumenTotal": "",
		"tipoPedido": "",
		"disenho": "",
		"frecuencia": "",
		"volumenAvance": "",
		"totalTiquete": "",
		"numeroTiquete": ""
	  }
	]
}